pkg/__init__.py
pkg/apt_data_set_generator.py
pkg/apt_repo.py
pkg/apt_runner.py
pkg/aptmd.py
pkg/metalink.py
pkg/pkgformat.py
pkg/pkglist.py
pkg/repo.py
pkg/repomd.py
pkg/runner.py
pkg/version.py
pkg-0.2.dist-info/METADATA
pkg-0.2.dist-info/WHEEL
pkg-0.2.dist-info/top_level.txt
pkg-0.2.dist-info/RECORD
