Metadata-Version: 2.1
Name: pkg
Version: 0.2
Summary: Python scripts dealing with software packages used in building applications and systems
Home-page: https://github.com/joaomdsc/pkg
Author: João Moreira de Sá Coutinho
Author-email: joao.moreiradsc@gmail.com
License: UNKNOWN
Platform: UNKNOWN
Classifier: Programming Language :: Python :: 3
Classifier: License :: OSI Approved :: GNU General Public License v3 or later (GPLv3+)
Classifier: Operating System :: OS Independent
Requires-Python: >=3.7.3
